{
	"country": "WORLD",
	"league": "World Cup - Round 3",
	"matchTime": "30.11.2022 20:00",
	"matchState": "Finished",
	"homeTeamName": "Poland",
	"awayTeamName": "Argentina",
	"homeTeamScore": "0",
	"awayTeamScore": "2",
	"statistics": [
		{
			"Ball Possession": {
				"homeTeamValue": "27%",
				"awayTeamValue": "73%"
			}
		},
		{
			"Goal Attempts": {
				"homeTeamValue": "4",
				"awayTeamValue": "25"
			}
		},
		{
			"Shots on Goal": {
				"homeTeamValue": "0",
				"awayTeamValue": "13"
			}
		},
		{
			"Shots off Goal": {
				"homeTeamValue": "2",
				"awayTeamValue": "8"
			}
		},
		{
			"Blocked Shots": {
				"homeTeamValue": "2",
				"awayTeamValue": "4"
			}
		},
		{
			"Free Kicks": {
				"homeTeamValue": "12",
				"awayTeamValue": "5"
			}
		},
		{
			"Corner Kicks": {
				"homeTeamValue": "1",
				"awayTeamValue": "9"
			}
		},
		{
			"Offsides": {
				"homeTeamValue": "0",
				"awayTeamValue": "0"
			}
		},
		{
			"Throw-in": {
				"homeTeamValue": "16",
				"awayTeamValue": "18"
			}
		},
		{
			"Goalkeeper Saves": {
				"homeTeamValue": "11",
				"awayTeamValue": "0"
			}
		},
		{
			"Fouls": {
				"homeTeamValue": "6",
				"awayTeamValue": "11"
			}
		},
		{
			"Yellow Cards": {
				"homeTeamValue": "1",
				"awayTeamValue": "1"
			}
		},
		{
			"Total Passes": {
				"homeTeamValue": "321",
				"awayTeamValue": "862"
			}
		},
		{
			"Completed Passes": {
				"homeTeamValue": "261",
				"awayTeamValue": "814"
			}
		},
		{
			"Tackles": {
				"homeTeamValue": "17",
				"awayTeamValue": "13"
			}
		},
		{
			"Attacks": {
				"homeTeamValue": "73",
				"awayTeamValue": "170"
			}
		},
		{
			"Dangerous Attacks": {
				"homeTeamValue": "14",
				"awayTeamValue": "89"
			}
		}
	]
}