{
	"country": "EUROPE",
	"league": "Champions League - Round 2",
	"matchTime": "18.10.2022 18:30",
	"matchState": "Finished",
	"homeTeamName": "Peristeri",
	"awayTeamName": "Tenerife",
	"homeTeamScore": "88",
	"awayTeamScore": "81",
	"statistics": [
		{
			"Field Goals Attempted": {
				"homeTeamValue": "63",
				"awayTeamValue": "57"
			}
		},
		{
			"Field Goals Made": {
				"homeTeamValue": "32",
				"awayTeamValue": "30"
			}
		},
		{
			"Field Goals %": {
				"homeTeamValue": "50.8%",
				"awayTeamValue": "52.6%"
			}
		},
		{
			"2-Point Field G. Attempted": {
				"homeTeamValue": "34",
				"awayTeamValue": "40"
			}
		},
		{
			"2-Point Field Goals Made": {
				"homeTeamValue": "20",
				"awayTeamValue": "23"
			}
		},
		{
			"2-Point Field Goals %": {
				"homeTeamValue": "58.8%",
				"awayTeamValue": "57.5%"
			}
		},
		{
			"3-Point Field G. Attempted": {
				"homeTeamValue": "29",
				"awayTeamValue": "17"
			}
		},
		{
			"3-Point Field Goals Made": {
				"homeTeamValue": "12",
				"awayTeamValue": "7"
			}
		},
		{
			"3-Point Field Goals %": {
				"homeTeamValue": "41.4%",
				"awayTeamValue": "41.2%"
			}
		},
		{
			"Free Throws Attempted": {
				"homeTeamValue": "18",
				"awayTeamValue": "21"
			}
		},
		{
			"Free Throws Made": {
				"homeTeamValue": "12",
				"awayTeamValue": "14"
			}
		},
		{
			"Free Throws %": {
				"homeTeamValue": "66.7%",
				"awayTeamValue": "66.7%"
			}
		},
		{
			"Offensive Rebounds": {
				"homeTeamValue": "18",
				"awayTeamValue": "9"
			}
		},
		{
			"Defensive Rebounds": {
				"homeTeamValue": "20",
				"awayTeamValue": "15"
			}
		},
		{
			"Total Rebounds": {
				"homeTeamValue": "38",
				"awayTeamValue": "24"
			}
		},
		{
			"Assists": {
				"homeTeamValue": "18",
				"awayTeamValue": "19"
			}
		},
		{
			"Blocks": {
				"homeTeamValue": "1",
				"awayTeamValue": "2"
			}
		},
		{
			"Turnovers": {
				"homeTeamValue": "14",
				"awayTeamValue": "14"
			}
		},
		{
			"Steals": {
				"homeTeamValue": "7",
				"awayTeamValue": "8"
			}
		},
		{
			"Personal Fouls": {
				"homeTeamValue": "19",
				"awayTeamValue": "19"
			}
		}
	]
}