{
	"country": "USA",
	"league": "MLS",
	"matchTime": "23.05.2022 02:00",
	"matchState": "Finished",
	"homeTeamName": "Austin FC",
	"awayTeamName": "Orlando City",
	"homeTeamScore": "2",
	"awayTeamScore": "2",
	"statistics": [
		{
			"Ball Possession": {
				"homeTeamValue": "71%",
				"awayTeamValue": "29%"
			}
		},
		{
			"Goal Attempts": {
				"homeTeamValue": "22",
				"awayTeamValue": "12"
			}
		},
		{
			"Shots on Goal": {
				"homeTeamValue": "5",
				"awayTeamValue": "7"
			}
		},
		{
			"Shots off Goal": {
				"homeTeamValue": "10",
				"awayTeamValue": "4"
			}
		},
		{
			"Blocked Shots": {
				"homeTeamValue": "7",
				"awayTeamValue": "1"
			}
		},
		{
			"Free Kicks": {
				"homeTeamValue": "10",
				"awayTeamValue": "15"
			}
		},
		{
			"Corner Kicks": {
				"homeTeamValue": "10",
				"awayTeamValue": "2"
			}
		},
		{
			"Offsides": {
				"homeTeamValue": "0",
				"awayTeamValue": "1"
			}
		},
		{
			"Throw-in": {
				"homeTeamValue": "16",
				"awayTeamValue": "15"
			}
		},
		{
			"Goalkeeper Saves": {
				"homeTeamValue": "5",
				"awayTeamValue": "3"
			}
		},
		{
			"Fouls": {
				"homeTeamValue": "16",
				"awayTeamValue": "10"
			}
		},
		{
			"Red Cards": {
				"homeTeamValue": "0",
				"awayTeamValue": "2"
			}
		},
		{
			"Yellow Cards": {
				"homeTeamValue": "0",
				"awayTeamValue": "5"
			}
		},
		{
			"Total Passes": {
				"homeTeamValue": "560",
				"awayTeamValue": "234"
			}
		},
		{
			"Attacks": {
				"homeTeamValue": "119",
				"awayTeamValue": "61"
			}
		},
		{
			"Dangerous Attacks": {
				"homeTeamValue": "77",
				"awayTeamValue": "24"
			}
		}
	]
}