{
	"country": "EUROPE",
	"league": "Champions League - Group Stage - Round 6",
	"matchTime": "02.11.2022 21:00",
	"matchState": "Finished",
	"homeTeamName": "Chelsea",
	"awayTeamName": "D. Zagreb",
	"homeTeamScore": "2",
	"awayTeamScore": "1",
	"statistics": [
		{
			"Ball Possession": {
				"homeTeamValue": "57%",
				"awayTeamValue": "43%"
			}
		},
		{
			"Goal Attempts": {
				"homeTeamValue": "22",
				"awayTeamValue": "7"
			}
		},
		{
			"Shots on Goal": {
				"homeTeamValue": "6",
				"awayTeamValue": "2"
			}
		},
		{
			"Shots off Goal": {
				"homeTeamValue": "12",
				"awayTeamValue": "1"
			}
		},
		{
			"Blocked Shots": {
				"homeTeamValue": "4",
				"awayTeamValue": "4"
			}
		},
		{
			"Free Kicks": {
				"homeTeamValue": "15",
				"awayTeamValue": "17"
			}
		},
		{
			"Corner Kicks": {
				"homeTeamValue": "9",
				"awayTeamValue": "3"
			}
		},
		{
			"Offsides": {
				"homeTeamValue": "0",
				"awayTeamValue": "0"
			}
		},
		{
			"Throw-in": {
				"homeTeamValue": "20",
				"awayTeamValue": "15"
			}
		},
		{
			"Goalkeeper Saves": {
				"homeTeamValue": "1",
				"awayTeamValue": "4"
			}
		},
		{
			"Fouls": {
				"homeTeamValue": "17",
				"awayTeamValue": "16"
			}
		},
		{
			"Yellow Cards": {
				"homeTeamValue": "1",
				"awayTeamValue": "3"
			}
		},
		{
			"Total Passes": {
				"homeTeamValue": "604",
				"awayTeamValue": "417"
			}
		},
		{
			"Completed Passes": {
				"homeTeamValue": "547",
				"awayTeamValue": "340"
			}
		},
		{
			"Tackles": {
				"homeTeamValue": "10",
				"awayTeamValue": "13"
			}
		},
		{
			"Attacks": {
				"homeTeamValue": "131",
				"awayTeamValue": "67"
			}
		},
		{
			"Dangerous Attacks": {
				"homeTeamValue": "69",
				"awayTeamValue": "25"
			}
		}
	]
}