{
	"country": "GERMANY",
	"league": "Bundesliga - Round 7",
	"matchTime": "16.09.2022 20:30",
	"matchState": "Finished",
	"homeTeamName": "Mainz",
	"awayTeamName": "Hertha Berlin",
	"homeTeamScore": "1",
	"awayTeamScore": "1",
	"statistics": [
		{
			"Ball Possession": {
				"homeTeamValue": "56%",
				"awayTeamValue": "44%"
			}
		},
		{
			"Goal Attempts": {
				"homeTeamValue": "12",
				"awayTeamValue": "4"
			}
		},
		{
			"Shots on Goal": {
				"homeTeamValue": "2",
				"awayTeamValue": "2"
			}
		},
		{
			"Shots off Goal": {
				"homeTeamValue": "10",
				"awayTeamValue": "2"
			}
		},
		{
			"Free Kicks": {
				"homeTeamValue": "13",
				"awayTeamValue": "16"
			}
		},
		{
			"Corner Kicks": {
				"homeTeamValue": "4",
				"awayTeamValue": "3"
			}
		},
		{
			"Offsides": {
				"homeTeamValue": "4",
				"awayTeamValue": "2"
			}
		},
		{
			"Throw-in": {
				"homeTeamValue": "33",
				"awayTeamValue": "20"
			}
		},
		{
			"Goalkeeper Saves": {
				"homeTeamValue": "1",
				"awayTeamValue": "1"
			}
		},
		{
			"Fouls": {
				"homeTeamValue": "12",
				"awayTeamValue": "10"
			}
		},
		{
			"Yellow Cards": {
				"homeTeamValue": "3",
				"awayTeamValue": "5"
			}
		},
		{
			"Total Passes": {
				"homeTeamValue": "446",
				"awayTeamValue": "333"
			}
		},
		{
			"Completed Passes": {
				"homeTeamValue": "312",
				"awayTeamValue": "233"
			}
		},
		{
			"Attacks": {
				"homeTeamValue": "123",
				"awayTeamValue": "95"
			}
		},
		{
			"Dangerous Attacks": {
				"homeTeamValue": "48",
				"awayTeamValue": "31"
			}
		}
	]
}