{
	"country": "USA",
	"league": "NBA",
	"matchTime": "02.11.2022 00:30",
	"matchState": "Finished",
	"homeTeamName": "Miami Heat",
	"awayTeamName": "Golden State Warriors",
	"homeTeamScore": "116",
	"awayTeamScore": "109",
	"statistics": [
		{
			"Field Goals Attempted": {
				"homeTeamValue": "88",
				"awayTeamValue": "84"
			}
		},
		{
			"Field Goals Made": {
				"homeTeamValue": "40",
				"awayTeamValue": "39"
			}
		},
		{
			"Field Goals %": {
				"homeTeamValue": "45.5%",
				"awayTeamValue": "46.4%"
			}
		},
		{
			"2-Point Field G. Attempted": {
				"homeTeamValue": "46",
				"awayTeamValue": "35"
			}
		},
		{
			"2-Point Field Goals Made": {
				"homeTeamValue": "24",
				"awayTeamValue": "21"
			}
		},
		{
			"2-Point Field Goals %": {
				"homeTeamValue": "52.2%",
				"awayTeamValue": "60%"
			}
		},
		{
			"3-Point Field G. Attempted": {
				"homeTeamValue": "42",
				"awayTeamValue": "49"
			}
		},
		{
			"3-Point Field Goals Made": {
				"homeTeamValue": "16",
				"awayTeamValue": "18"
			}
		},
		{
			"3-Point Field Goals %": {
				"homeTeamValue": "38.1%",
				"awayTeamValue": "36.7%"
			}
		},
		{
			"Free Throws Attempted": {
				"homeTeamValue": "20",
				"awayTeamValue": "17"
			}
		},
		{
			"Free Throws Made": {
				"homeTeamValue": "20",
				"awayTeamValue": "13"
			}
		},
		{
			"Free Throws %": {
				"homeTeamValue": "100%",
				"awayTeamValue": "76.5%"
			}
		},
		{
			"Offensive Rebounds": {
				"homeTeamValue": "9",
				"awayTeamValue": "10"
			}
		},
		{
			"Defensive Rebounds": {
				"homeTeamValue": "30",
				"awayTeamValue": "31"
			}
		},
		{
			"Total Rebounds": {
				"homeTeamValue": "39",
				"awayTeamValue": "41"
			}
		},
		{
			"Assists": {
				"homeTeamValue": "32",
				"awayTeamValue": "31"
			}
		},
		{
			"Blocks": {
				"homeTeamValue": "3",
				"awayTeamValue": "5"
			}
		},
		{
			"Turnovers": {
				"homeTeamValue": "15",
				"awayTeamValue": "20"
			}
		},
		{
			"Steals": {
				"homeTeamValue": "7",
				"awayTeamValue": "8"
			}
		},
		{
			"Personal Fouls": {
				"homeTeamValue": "16",
				"awayTeamValue": "22"
			}
		},
		{
			"Technical Fouls": {
				"homeTeamValue": "1",
				"awayTeamValue": "2"
			}
		}
	]
}