{
	"country": "USA",
	"league": "NBA",
	"matchTime": "29.10.2022 04:00",
	"matchState": "Finished",
	"homeTeamName": "Phoenix Suns",
	"awayTeamName": "New Orleans Pelicans",
	"homeTeamScore": "124",
	"awayTeamScore": "111",
	"statistics": [
		{
			"Field Goals Attempted": {
				"homeTeamValue": "92",
				"awayTeamValue": "86"
			}
		},
		{
			"Field Goals Made": {
				"homeTeamValue": "48",
				"awayTeamValue": "38"
			}
		},
		{
			"Field Goals %": {
				"homeTeamValue": "52.2%",
				"awayTeamValue": "44.2%"
			}
		},
		{
			"2-Point Field G. Attempted": {
				"homeTeamValue": "59",
				"awayTeamValue": "49"
			}
		},
		{
			"2-Point Field Goals Made": {
				"homeTeamValue": "38",
				"awayTeamValue": "23"
			}
		},
		{
			"2-Point Field Goals %": {
				"homeTeamValue": "64.4%",
				"awayTeamValue": "46.9%"
			}
		},
		{
			"3-Point Field G. Attempted": {
				"homeTeamValue": "33",
				"awayTeamValue": "37"
			}
		},
		{
			"3-Point Field Goals Made": {
				"homeTeamValue": "10",
				"awayTeamValue": "15"
			}
		},
		{
			"3-Point Field Goals %": {
				"homeTeamValue": "30.3%",
				"awayTeamValue": "40.5%"
			}
		},
		{
			"Free Throws Attempted": {
				"homeTeamValue": "20",
				"awayTeamValue": "22"
			}
		},
		{
			"Free Throws Made": {
				"homeTeamValue": "18",
				"awayTeamValue": "20"
			}
		},
		{
			"Free Throws %": {
				"homeTeamValue": "90%",
				"awayTeamValue": "90.9%"
			}
		},
		{
			"Offensive Rebounds": {
				"homeTeamValue": "14",
				"awayTeamValue": "9"
			}
		},
		{
			"Defensive Rebounds": {
				"homeTeamValue": "33",
				"awayTeamValue": "24"
			}
		},
		{
			"Total Rebounds": {
				"homeTeamValue": "47",
				"awayTeamValue": "33"
			}
		},
		{
			"Assists": {
				"homeTeamValue": "33",
				"awayTeamValue": "25"
			}
		},
		{
			"Blocks": {
				"homeTeamValue": "7",
				"awayTeamValue": "1"
			}
		},
		{
			"Turnovers": {
				"homeTeamValue": "12",
				"awayTeamValue": "14"
			}
		},
		{
			"Steals": {
				"homeTeamValue": "7",
				"awayTeamValue": "10"
			}
		},
		{
			"Personal Fouls": {
				"homeTeamValue": "18",
				"awayTeamValue": "21"
			}
		},
		{
			"Technical Fouls": {
				"homeTeamValue": "0",
				"awayTeamValue": "0"
			}
		}
	]
}