{
	"country": "ASIA",
	"league": "World Cup - Qualification - Second stage - Round 8",
	"matchTime": "11.06.2021 18:45",
	"matchState": "Finished",
	"homeTeamName": "Indonesia",
	"awayTeamName": "United Arab Emirates",
	"homeTeamScore": "0",
	"awayTeamScore": "5",
	"statistics": [
		{
			"Ball Possession": {
				"homeTeamValue": "28%",
				"awayTeamValue": "72%"
			}
		},
		{
			"Goal Attempts": {
				"homeTeamValue": "7",
				"awayTeamValue": "19"
			}
		},
		{
			"Shots on Goal": {
				"homeTeamValue": "2",
				"awayTeamValue": "12"
			}
		},
		{
			"Shots off Goal": {
				"homeTeamValue": "2",
				"awayTeamValue": "4"
			}
		},
		{
			"Blocked Shots": {
				"homeTeamValue": "3",
				"awayTeamValue": "3"
			}
		},
		{
			"Free Kicks": {
				"homeTeamValue": "14",
				"awayTeamValue": "16"
			}
		},
		{
			"Corner Kicks": {
				"homeTeamValue": "6",
				"awayTeamValue": "3"
			}
		},
		{
			"Offsides": {
				"homeTeamValue": "3",
				"awayTeamValue": "5"
			}
		},
		{
			"Throw-in": {
				"homeTeamValue": "13",
				"awayTeamValue": "7"
			}
		},
		{
			"Goalkeeper Saves": {
				"homeTeamValue": "7",
				"awayTeamValue": "2"
			}
		},
		{
			"Fouls": {
				"homeTeamValue": "14",
				"awayTeamValue": "10"
			}
		},
		{
			"Yellow Cards": {
				"homeTeamValue": "1",
				"awayTeamValue": "0"
			}
		},
		{
			"Total Passes": {
				"homeTeamValue": "314",
				"awayTeamValue": "826"
			}
		},
		{
			"Attacks": {
				"homeTeamValue": "56",
				"awayTeamValue": "92"
			}
		},
		{
			"Dangerous Attacks": {
				"homeTeamValue": "53",
				"awayTeamValue": "70"
			}
		}
	]
}