{
	"country": "EUROPE",
	"league": "Europa Conference League - Qualification - Quarter-finals",
	"matchTime": "28.07.2022 19:00",
	"matchState": "Finished",
	"homeTeamName": "Advancing to next roundNeftci Baku (Aze)",
	"awayTeamName": "Aris (Cyp)",
	"homeTeamScore": "3",
	"awayTeamScore": "0",
	"statistics": [
		{
			"Ball Possession": {
				"homeTeamValue": "52%",
				"awayTeamValue": "48%"
			}
		},
		{
			"Goal Attempts": {
				"homeTeamValue": "11",
				"awayTeamValue": "9"
			}
		},
		{
			"Shots on Goal": {
				"homeTeamValue": "4",
				"awayTeamValue": "3"
			}
		},
		{
			"Shots off Goal": {
				"homeTeamValue": "5",
				"awayTeamValue": "3"
			}
		},
		{
			"Blocked Shots": {
				"homeTeamValue": "2",
				"awayTeamValue": "3"
			}
		},
		{
			"Free Kicks": {
				"homeTeamValue": "25",
				"awayTeamValue": "16"
			}
		},
		{
			"Corner Kicks": {
				"homeTeamValue": "2",
				"awayTeamValue": "6"
			}
		},
		{
			"Offsides": {
				"homeTeamValue": "2",
				"awayTeamValue": "2"
			}
		},
		{
			"Throw-in": {
				"homeTeamValue": "36",
				"awayTeamValue": "28"
			}
		},
		{
			"Goalkeeper Saves": {
				"homeTeamValue": "3",
				"awayTeamValue": "1"
			}
		},
		{
			"Fouls": {
				"homeTeamValue": "9",
				"awayTeamValue": "12"
			}
		},
		{
			"Red Cards": {
				"homeTeamValue": "0",
				"awayTeamValue": "1"
			}
		},
		{
			"Yellow Cards": {
				"homeTeamValue": "4",
				"awayTeamValue": "6"
			}
		},
		{
			"Attacks": {
				"homeTeamValue": "96",
				"awayTeamValue": "75"
			}
		},
		{
			"Dangerous Attacks": {
				"homeTeamValue": "67",
				"awayTeamValue": "53"
			}
		}
	]
}