{
	"country": "USA",
	"league": "NBA",
	"matchTime": "04.12.2022 02:30",
	"matchState": "Finished",
	"homeTeamName": "Golden State Warriors",
	"awayTeamName": "Houston Rockets",
	"homeTeamScore": "120",
	"awayTeamScore": "101",
	"statistics": [
		{
			"Field Goals Attempted": {
				"homeTeamValue": "85",
				"awayTeamValue": "91"
			}
		},
		{
			"Field Goals Made": {
				"homeTeamValue": "45",
				"awayTeamValue": "40"
			}
		},
		{
			"Field Goals %": {
				"homeTeamValue": "52.9%",
				"awayTeamValue": "44%"
			}
		},
		{
			"2-Point Field G. Attempted": {
				"homeTeamValue": "33",
				"awayTeamValue": "63"
			}
		},
		{
			"2-Point Field Goals Made": {
				"homeTeamValue": "20",
				"awayTeamValue": "37"
			}
		},
		{
			"2-Point Field Goals %": {
				"homeTeamValue": "60.6%",
				"awayTeamValue": "58.7%"
			}
		},
		{
			"3-Point Field G. Attempted": {
				"homeTeamValue": "52",
				"awayTeamValue": "28"
			}
		},
		{
			"3-Point Field Goals Made": {
				"homeTeamValue": "25",
				"awayTeamValue": "3"
			}
		},
		{
			"3-Point Field Goals %": {
				"homeTeamValue": "48.1%",
				"awayTeamValue": "10.7%"
			}
		},
		{
			"Free Throws Attempted": {
				"homeTeamValue": "10",
				"awayTeamValue": "20"
			}
		},
		{
			"Free Throws Made": {
				"homeTeamValue": "5",
				"awayTeamValue": "18"
			}
		},
		{
			"Free Throws %": {
				"homeTeamValue": "50%",
				"awayTeamValue": "90%"
			}
		},
		{
			"Offensive Rebounds": {
				"homeTeamValue": "6",
				"awayTeamValue": "14"
			}
		},
		{
			"Defensive Rebounds": {
				"homeTeamValue": "29",
				"awayTeamValue": "31"
			}
		},
		{
			"Total Rebounds": {
				"homeTeamValue": "35",
				"awayTeamValue": "45"
			}
		},
		{
			"Assists": {
				"homeTeamValue": "34",
				"awayTeamValue": "17"
			}
		},
		{
			"Blocks": {
				"homeTeamValue": "5",
				"awayTeamValue": "4"
			}
		},
		{
			"Turnovers": {
				"homeTeamValue": "14",
				"awayTeamValue": "15"
			}
		},
		{
			"Steals": {
				"homeTeamValue": "8",
				"awayTeamValue": "6"
			}
		},
		{
			"Personal Fouls": {
				"homeTeamValue": "24",
				"awayTeamValue": "14"
			}
		},
		{
			"Technical Fouls": {
				"homeTeamValue": "1",
				"awayTeamValue": "0"
			}
		}
	]
}