{
	"country": "USA",
	"league": "NBA",
	"matchTime": "23.10.2022 03:00",
	"matchState": "Finished",
	"homeTeamName": "Denver Nuggets",
	"awayTeamName": "Oklahoma City Thunder",
	"homeTeamScore": "122",
	"awayTeamScore": "117",
	"statistics": [
		{
			"Field Goals Attempted": {
				"homeTeamValue": "85",
				"awayTeamValue": "94"
			}
		},
		{
			"Field Goals Made": {
				"homeTeamValue": "42",
				"awayTeamValue": "42"
			}
		},
		{
			"Field Goals %": {
				"homeTeamValue": "49.4%",
				"awayTeamValue": "44.7%"
			}
		},
		{
			"2-Point Field G. Attempted": {
				"homeTeamValue": "47",
				"awayTeamValue": "56"
			}
		},
		{
			"2-Point Field Goals Made": {
				"homeTeamValue": "22",
				"awayTeamValue": "27"
			}
		},
		{
			"2-Point Field Goals %": {
				"homeTeamValue": "46.8%",
				"awayTeamValue": "48.2%"
			}
		},
		{
			"3-Point Field G. Attempted": {
				"homeTeamValue": "38",
				"awayTeamValue": "38"
			}
		},
		{
			"3-Point Field Goals Made": {
				"homeTeamValue": "20",
				"awayTeamValue": "15"
			}
		},
		{
			"3-Point Field Goals %": {
				"homeTeamValue": "52.6%",
				"awayTeamValue": "39.5%"
			}
		},
		{
			"Free Throws Attempted": {
				"homeTeamValue": "31",
				"awayTeamValue": "23"
			}
		},
		{
			"Free Throws Made": {
				"homeTeamValue": "18",
				"awayTeamValue": "18"
			}
		},
		{
			"Free Throws %": {
				"homeTeamValue": "58.1%",
				"awayTeamValue": "78.3%"
			}
		},
		{
			"Offensive Rebounds": {
				"homeTeamValue": "9",
				"awayTeamValue": "10"
			}
		},
		{
			"Defensive Rebounds": {
				"homeTeamValue": "37",
				"awayTeamValue": "37"
			}
		},
		{
			"Total Rebounds": {
				"homeTeamValue": "46",
				"awayTeamValue": "47"
			}
		},
		{
			"Assists": {
				"homeTeamValue": "33",
				"awayTeamValue": "29"
			}
		},
		{
			"Blocks": {
				"homeTeamValue": "7",
				"awayTeamValue": "5"
			}
		},
		{
			"Turnovers": {
				"homeTeamValue": "18",
				"awayTeamValue": "12"
			}
		},
		{
			"Steals": {
				"homeTeamValue": "5",
				"awayTeamValue": "10"
			}
		},
		{
			"Personal Fouls": {
				"homeTeamValue": "21",
				"awayTeamValue": "27"
			}
		},
		{
			"Technical Fouls": {
				"homeTeamValue": "1",
				"awayTeamValue": "0"
			}
		}
	]
}