{
	"country": "EUROPE",
	"league": "Champions League - Round 3",
	"matchTime": "25.10.2022 18:30",
	"matchState": "Finished",
	"homeTeamName": "Benfica",
	"awayTeamName": "Manresa",
	"homeTeamScore": "78",
	"awayTeamScore": "97",
	"statistics": [
		{
			"Field Goals Attempted": {
				"homeTeamValue": "66",
				"awayTeamValue": "70"
			}
		},
		{
			"Field Goals Made": {
				"homeTeamValue": "30",
				"awayTeamValue": "31"
			}
		},
		{
			"Field Goals %": {
				"homeTeamValue": "45.5%",
				"awayTeamValue": "44.3%"
			}
		},
		{
			"2-Point Field G. Attempted": {
				"homeTeamValue": "45",
				"awayTeamValue": "41"
			}
		},
		{
			"2-Point Field Goals Made": {
				"homeTeamValue": "23",
				"awayTeamValue": "18"
			}
		},
		{
			"2-Point Field Goals %": {
				"homeTeamValue": "51.1%",
				"awayTeamValue": "43.9%"
			}
		},
		{
			"3-Point Field G. Attempted": {
				"homeTeamValue": "21",
				"awayTeamValue": "29"
			}
		},
		{
			"3-Point Field Goals Made": {
				"homeTeamValue": "7",
				"awayTeamValue": "13"
			}
		},
		{
			"3-Point Field Goals %": {
				"homeTeamValue": "33.3%",
				"awayTeamValue": "44.8%"
			}
		},
		{
			"Free Throws Attempted": {
				"homeTeamValue": "15",
				"awayTeamValue": "26"
			}
		},
		{
			"Free Throws Made": {
				"homeTeamValue": "11",
				"awayTeamValue": "22"
			}
		},
		{
			"Free Throws %": {
				"homeTeamValue": "73.3%",
				"awayTeamValue": "84.6%"
			}
		},
		{
			"Offensive Rebounds": {
				"homeTeamValue": "14",
				"awayTeamValue": "13"
			}
		},
		{
			"Defensive Rebounds": {
				"homeTeamValue": "26",
				"awayTeamValue": "25"
			}
		},
		{
			"Total Rebounds": {
				"homeTeamValue": "40",
				"awayTeamValue": "38"
			}
		},
		{
			"Assists": {
				"homeTeamValue": "23",
				"awayTeamValue": "24"
			}
		},
		{
			"Blocks": {
				"homeTeamValue": "4",
				"awayTeamValue": "4"
			}
		},
		{
			"Turnovers": {
				"homeTeamValue": "20",
				"awayTeamValue": "12"
			}
		},
		{
			"Steals": {
				"homeTeamValue": "8",
				"awayTeamValue": "5"
			}
		},
		{
			"Personal Fouls": {
				"homeTeamValue": "21",
				"awayTeamValue": "20"
			}
		}
	]
}