{
	"country": "GERMANY",
	"league": "Bundesliga - Round 10",
	"matchTime": "16.10.2022 15:30",
	"matchState": "Finished",
	"homeTeamName": "FC Koln",
	"awayTeamName": "Augsburg",
	"homeTeamScore": "3",
	"awayTeamScore": "2",
	"statistics": [
		{
			"Ball Possession": {
				"homeTeamValue": "60%",
				"awayTeamValue": "40%"
			}
		},
		{
			"Goal Attempts": {
				"homeTeamValue": "14",
				"awayTeamValue": "7"
			}
		},
		{
			"Shots on Goal": {
				"homeTeamValue": "6",
				"awayTeamValue": "3"
			}
		},
		{
			"Shots off Goal": {
				"homeTeamValue": "8",
				"awayTeamValue": "4"
			}
		},
		{
			"Free Kicks": {
				"homeTeamValue": "16",
				"awayTeamValue": "10"
			}
		},
		{
			"Corner Kicks": {
				"homeTeamValue": "5",
				"awayTeamValue": "3"
			}
		},
		{
			"Offsides": {
				"homeTeamValue": "0",
				"awayTeamValue": "2"
			}
		},
		{
			"Throw-in": {
				"homeTeamValue": "32",
				"awayTeamValue": "19"
			}
		},
		{
			"Goalkeeper Saves": {
				"homeTeamValue": "1",
				"awayTeamValue": "3"
			}
		},
		{
			"Fouls": {
				"homeTeamValue": "11",
				"awayTeamValue": "15"
			}
		},
		{
			"Yellow Cards": {
				"homeTeamValue": "2",
				"awayTeamValue": "4"
			}
		},
		{
			"Total Passes": {
				"homeTeamValue": "471",
				"awayTeamValue": "258"
			}
		},
		{
			"Completed Passes": {
				"homeTeamValue": "372",
				"awayTeamValue": "163"
			}
		},
		{
			"Attacks": {
				"homeTeamValue": "114",
				"awayTeamValue": "77"
			}
		},
		{
			"Dangerous Attacks": {
				"homeTeamValue": "83",
				"awayTeamValue": "34"
			}
		}
	]
}