{
	"country": "ASIA",
	"league": "World Cup - Qualification - Second stage - Round 10",
	"matchTime": "15.06.2021 20:00",
	"matchState": "Finished",
	"homeTeamName": "Palestine",
	"awayTeamName": "Yemen",
	"homeTeamScore": "3",
	"awayTeamScore": "0",
	"statistics": [
		{
			"Ball Possession": {
				"homeTeamValue": "51%",
				"awayTeamValue": "49%"
			}
		},
		{
			"Goal Attempts": {
				"homeTeamValue": "19",
				"awayTeamValue": "2"
			}
		},
		{
			"Shots on Goal": {
				"homeTeamValue": "12",
				"awayTeamValue": "0"
			}
		},
		{
			"Shots off Goal": {
				"homeTeamValue": "7",
				"awayTeamValue": "2"
			}
		},
		{
			"Free Kicks": {
				"homeTeamValue": "12",
				"awayTeamValue": "20"
			}
		},
		{
			"Corner Kicks": {
				"homeTeamValue": "9",
				"awayTeamValue": "1"
			}
		},
		{
			"Offsides": {
				"homeTeamValue": "2",
				"awayTeamValue": "2"
			}
		},
		{
			"Throw-in": {
				"homeTeamValue": "20",
				"awayTeamValue": "22"
			}
		},
		{
			"Goalkeeper Saves": {
				"homeTeamValue": "0",
				"awayTeamValue": "9"
			}
		},
		{
			"Fouls": {
				"homeTeamValue": "17",
				"awayTeamValue": "11"
			}
		},
		{
			"Yellow Cards": {
				"homeTeamValue": "1",
				"awayTeamValue": "1"
			}
		},
		{
			"Attacks": {
				"homeTeamValue": "68",
				"awayTeamValue": "62"
			}
		},
		{
			"Dangerous Attacks": {
				"homeTeamValue": "66",
				"awayTeamValue": "27"
			}
		}
	]
}