{
	"country": "SPAIN",
	"league": "LaLiga - Round 12",
	"matchTime": "29.10.2022 21:00",
	"matchState": "Finished",
	"homeTeamName": "Valencia",
	"awayTeamName": "Barcelona",
	"homeTeamScore": "0",
	"awayTeamScore": "1",
	"statistics": [
		{
			"Ball Possession": {
				"homeTeamValue": "33%",
				"awayTeamValue": "67%"
			}
		},
		{
			"Goal Attempts": {
				"homeTeamValue": "3",
				"awayTeamValue": "13"
			}
		},
		{
			"Shots on Goal": {
				"homeTeamValue": "2",
				"awayTeamValue": "2"
			}
		},
		{
			"Shots off Goal": {
				"homeTeamValue": "1",
				"awayTeamValue": "7"
			}
		},
		{
			"Blocked Shots": {
				"homeTeamValue": "0",
				"awayTeamValue": "4"
			}
		},
		{
			"Free Kicks": {
				"homeTeamValue": "13",
				"awayTeamValue": "18"
			}
		},
		{
			"Corner Kicks": {
				"homeTeamValue": "3",
				"awayTeamValue": "10"
			}
		},
		{
			"Offsides": {
				"homeTeamValue": "1",
				"awayTeamValue": "3"
			}
		},
		{
			"Throw-in": {
				"homeTeamValue": "19",
				"awayTeamValue": "26"
			}
		},
		{
			"Goalkeeper Saves": {
				"homeTeamValue": "1",
				"awayTeamValue": "2"
			}
		},
		{
			"Fouls": {
				"homeTeamValue": "13",
				"awayTeamValue": "7"
			}
		},
		{
			"Yellow Cards": {
				"homeTeamValue": "4",
				"awayTeamValue": "5"
			}
		},
		{
			"Total Passes": {
				"homeTeamValue": "275",
				"awayTeamValue": "572"
			}
		},
		{
			"Completed Passes": {
				"homeTeamValue": "212",
				"awayTeamValue": "496"
			}
		},
		{
			"Tackles": {
				"homeTeamValue": "24",
				"awayTeamValue": "12"
			}
		},
		{
			"Attacks": {
				"homeTeamValue": "67",
				"awayTeamValue": "129"
			}
		},
		{
			"Dangerous Attacks": {
				"homeTeamValue": "32",
				"awayTeamValue": "65"
			}
		}
	]
}