{
	"id": "1w4xBgy5mda4tKL",
	"json": "{\"id\":\"1w4xBgy5mda4tKL\",\"url\":\"https://www.livesport.com/en/match/Y94DMzFh/#/match-summary/match-statistics/0\",\"loadedUrl\":\"https://www.livesport.com/en/match/Y94DMzFh/#/match-summary/match-statistics/0\",\"uniqueKey\":\"https://www.livesport.com/en/match/Y94DMzFh\",\"method\":\"GET\",\"noRetry\":false,\"retryCount\":0,\"errorMessages\":[],\"headers\":{},\"userData\":{\"label\":\"match\",\"__crawlee\":{\"state\":4}},\"handledAt\":\"2022-12-12T19:21:05.519Z\"}",
	"method": "GET",
	"orderNo": null,
	"retryCount": 0,
	"uniqueKey": "https://www.livesport.com/en/match/Y94DMzFh",
	"url": "https://www.livesport.com/en/match/Y94DMzFh/#/match-summary/match-statistics/0"
}