{
	"id": "2WHWEZ8Zet5YZoC",
	"json": "{\"id\":\"2WHWEZ8Zet5YZoC\",\"url\":\"https://www.livesport.com/en/match/tS5WmDl2/#/match-summary/match-statistics/0\",\"loadedUrl\":\"https://www.livesport.com/en/match/tS5WmDl2/#/match-summary/match-statistics/0\",\"uniqueKey\":\"https://www.livesport.com/en/match/tS5WmDl2\",\"method\":\"GET\",\"noRetry\":false,\"retryCount\":0,\"errorMessages\":[],\"headers\":{},\"userData\":{\"label\":\"match\",\"__crawlee\":{\"state\":4}},\"handledAt\":\"2022-12-12T19:39:53.735Z\"}",
	"method": "GET",
	"orderNo": null,
	"retryCount": 0,
	"uniqueKey": "https://www.livesport.com/en/match/tS5WmDl2",
	"url": "https://www.livesport.com/en/match/tS5WmDl2/#/match-summary/match-statistics/0"
}