{
	"id": "8F95cjNtilPBBjc",
	"json": "{\"id\":\"8F95cjNtilPBBjc\",\"url\":\"https://www.livesport.com/en/match/IBmkhQS9/#/match-summary/match-statistics/0\",\"loadedUrl\":\"https://www.livesport.com/en/match/IBmkhQS9/#/match-summary/match-statistics/0\",\"uniqueKey\":\"https://www.livesport.com/en/match/IBmkhQS9\",\"method\":\"GET\",\"noRetry\":false,\"retryCount\":0,\"errorMessages\":[],\"headers\":{},\"userData\":{\"label\":\"match\",\"__crawlee\":{\"state\":4}},\"handledAt\":\"2022-12-12T19:24:38.390Z\"}",
	"method": "GET",
	"orderNo": null,
	"retryCount": 0,
	"uniqueKey": "https://www.livesport.com/en/match/IBmkhQS9",
	"url": "https://www.livesport.com/en/match/IBmkhQS9/#/match-summary/match-statistics/0"
}