{
	"id": "Bz2fiwsSF2ZVrLX",
	"json": "{\"id\":\"Bz2fiwsSF2ZVrLX\",\"url\":\"https://www.livesport.com/en/match/GI98QUSB/#/match-summary/match-summary\",\"uniqueKey\":\"https://www.livesport.com/en/match/GI98QUSB\",\"method\":\"GET\",\"noRetry\":false,\"retryCount\":0,\"errorMessages\":[],\"headers\":{},\"userData\":{\"label\":\"match\"}}",
	"method": "GET",
	"orderNo": 1671053211960,
	"retryCount": 0,
	"uniqueKey": "https://www.livesport.com/en/match/GI98QUSB",
	"url": "https://www.livesport.com/en/match/GI98QUSB/#/match-summary/match-summary"
}