{
	"id": "COJTYAZ1s9475Bp",
	"json": "{\"id\":\"COJTYAZ1s9475Bp\",\"url\":\"https://www.livesport.com/en/match/4S1c3jir/#/match-summary/match-statistics/0\",\"loadedUrl\":\"https://www.livesport.com/en/match/4S1c3jir/#/match-summary/match-statistics/0\",\"uniqueKey\":\"https://www.livesport.com/en/match/4S1c3jir\",\"method\":\"GET\",\"noRetry\":false,\"retryCount\":0,\"errorMessages\":[],\"headers\":{},\"userData\":{\"label\":\"match\",\"__crawlee\":{\"state\":4}},\"handledAt\":\"2022-12-12T19:25:40.449Z\"}",
	"method": "GET",
	"orderNo": null,
	"retryCount": 0,
	"uniqueKey": "https://www.livesport.com/en/match/4S1c3jir",
	"url": "https://www.livesport.com/en/match/4S1c3jir/#/match-summary/match-statistics/0"
}