{
	"id": "CyjPXoxcp1IheKV",
	"json": "{\"id\":\"CyjPXoxcp1IheKV\",\"url\":\"https://www.livesport.com/en/match/QiDGktQf/#/match-summary/match-statistics/0\",\"loadedUrl\":\"https://www.livesport.com/en/match/QiDGktQf/#/match-summary/match-statistics/0\",\"uniqueKey\":\"https://www.livesport.com/en/match/QiDGktQf\",\"method\":\"GET\",\"noRetry\":false,\"retryCount\":0,\"errorMessages\":[],\"headers\":{},\"userData\":{\"label\":\"match\",\"__crawlee\":{\"state\":4}},\"handledAt\":\"2022-12-12T19:30:18.806Z\"}",
	"method": "GET",
	"orderNo": null,
	"retryCount": 0,
	"uniqueKey": "https://www.livesport.com/en/match/QiDGktQf",
	"url": "https://www.livesport.com/en/match/QiDGktQf/#/match-summary/match-statistics/0"
}