{
	"id": "EVrK1TEH18bslVn",
	"json": "{\"id\":\"EVrK1TEH18bslVn\",\"url\":\"https://www.livesport.com/en/match/2eXAg8pl/#/match-summary/match-summary\",\"uniqueKey\":\"https://www.livesport.com/en/match/2eXAg8pl\",\"method\":\"GET\",\"noRetry\":false,\"retryCount\":0,\"errorMessages\":[],\"headers\":{},\"userData\":{\"label\":\"match\"}}",
	"method": "GET",
	"orderNo": 1670968841931,
	"retryCount": 0,
	"uniqueKey": "https://www.livesport.com/en/match/2eXAg8pl",
	"url": "https://www.livesport.com/en/match/2eXAg8pl/#/match-summary/match-summary"
}