{
	"id": "HQaMM2KcwyK8Zo1",
	"json": "{\"id\":\"HQaMM2KcwyK8Zo1\",\"url\":\"https://www.livesport.com/en/match/xWMjLdjf/#/match-summary/match-statistics/0\",\"loadedUrl\":\"https://www.livesport.com/en/match/xWMjLdjf/#/match-summary/match-statistics/0\",\"uniqueKey\":\"https://www.livesport.com/en/match/xWMjLdjf\",\"method\":\"GET\",\"noRetry\":false,\"retryCount\":0,\"errorMessages\":[],\"headers\":{},\"userData\":{\"label\":\"match\",\"__crawlee\":{\"state\":4}},\"handledAt\":\"2022-12-12T19:37:43.676Z\"}",
	"method": "GET",
	"orderNo": null,
	"retryCount": 0,
	"uniqueKey": "https://www.livesport.com/en/match/xWMjLdjf",
	"url": "https://www.livesport.com/en/match/xWMjLdjf/#/match-summary/match-statistics/0"
}