{
	"id": "IBfVHDFtlnYDceL",
	"json": "{\"id\":\"IBfVHDFtlnYDceL\",\"url\":\"https://www.livesport.com/en/match/veaB2OmQ/#/match-summary/match-statistics/0\",\"loadedUrl\":\"https://www.livesport.com/en/match/veaB2OmQ/#/match-summary/match-statistics/0\",\"uniqueKey\":\"https://www.livesport.com/en/match/veaB2OmQ\",\"method\":\"GET\",\"noRetry\":false,\"retryCount\":0,\"errorMessages\":[],\"headers\":{},\"userData\":{\"label\":\"match\",\"__crawlee\":{\"state\":4}},\"handledAt\":\"2022-12-12T19:20:15.651Z\"}",
	"method": "GET",
	"orderNo": null,
	"retryCount": 0,
	"uniqueKey": "https://www.livesport.com/en/match/veaB2OmQ",
	"url": "https://www.livesport.com/en/match/veaB2OmQ/#/match-summary/match-statistics/0"
}