{
	"id": "IGzNYy0aB4blBtY",
	"json": "{\"id\":\"IGzNYy0aB4blBtY\",\"url\":\"https://www.livesport.com/en/match/OWr2gBC1/#/match-summary/match-statistics/0\",\"loadedUrl\":\"https://www.livesport.com/en/match/OWr2gBC1/#/match-summary/match-statistics/0\",\"uniqueKey\":\"https://www.livesport.com/en/match/OWr2gBC1\",\"method\":\"GET\",\"noRetry\":false,\"retryCount\":0,\"errorMessages\":[],\"headers\":{},\"userData\":{\"label\":\"match\",\"__crawlee\":{\"state\":4}},\"handledAt\":\"2022-12-12T19:37:37.172Z\"}",
	"method": "GET",
	"orderNo": null,
	"retryCount": 0,
	"uniqueKey": "https://www.livesport.com/en/match/OWr2gBC1",
	"url": "https://www.livesport.com/en/match/OWr2gBC1/#/match-summary/match-statistics/0"
}