{
	"id": "Jd2HBZA7Pxj8Eqn",
	"json": "{\"id\":\"Jd2HBZA7Pxj8Eqn\",\"url\":\"https://www.livesport.com/en/match/CtBpitIu/#/match-summary/match-summary\",\"uniqueKey\":\"https://www.livesport.com/en/match/CtBpitIu\",\"method\":\"GET\",\"noRetry\":false,\"retryCount\":0,\"errorMessages\":[],\"headers\":{},\"userData\":{\"label\":\"match\"}}",
	"method": "GET",
	"orderNo": 1671125561472,
	"retryCount": 0,
	"uniqueKey": "https://www.livesport.com/en/match/CtBpitIu",
	"url": "https://www.livesport.com/en/match/CtBpitIu/#/match-summary/match-summary"
}