{
	"id": "KPa6ZcDTjE09Jnc",
	"json": "{\"id\":\"KPa6ZcDTjE09Jnc\",\"url\":\"https://www.livesport.com/en/match/2RAR7nnL/#/match-summary/match-summary\",\"uniqueKey\":\"https://www.livesport.com/en/match/2RAR7nnL\",\"method\":\"GET\",\"noRetry\":false,\"retryCount\":0,\"errorMessages\":[],\"headers\":{},\"userData\":{\"label\":\"match\"}}",
	"method": "GET",
	"orderNo": 1670968841936,
	"retryCount": 0,
	"uniqueKey": "https://www.livesport.com/en/match/2RAR7nnL",
	"url": "https://www.livesport.com/en/match/2RAR7nnL/#/match-summary/match-summary"
}