{
	"id": "m6RksypPswqfLJ3",
	"json": "{\"id\":\"m6RksypPswqfLJ3\",\"url\":\"https://www.livesport.com/en/match/rci3M9tl/#/match-summary/match-summary\",\"loadedUrl\":\"https://www.livesport.com/en/match/rci3M9tl/#/match-summary/match-summary\",\"uniqueKey\":\"https://www.livesport.com/en/match/rci3M9tl\",\"method\":\"GET\",\"noRetry\":false,\"retryCount\":0,\"errorMessages\":[],\"headers\":{},\"userData\":{\"label\":\"match\",\"__crawlee\":{\"state\":4}},\"handledAt\":\"2022-12-13T22:00:48.170Z\"}",
	"method": "GET",
	"orderNo": null,
	"retryCount": 0,
	"uniqueKey": "https://www.livesport.com/en/match/rci3M9tl",
	"url": "https://www.livesport.com/en/match/rci3M9tl/#/match-summary/match-summary"
}