{
	"id": "sFh3q8NV9c7B3M8",
	"json": "{\"id\":\"sFh3q8NV9c7B3M8\",\"url\":\"https://www.livesport.com/en/match/EPqGnLRn/#/match-summary/match-summary\",\"uniqueKey\":\"https://www.livesport.com/en/match/EPqGnLRn\",\"method\":\"GET\",\"noRetry\":false,\"retryCount\":0,\"errorMessages\":[],\"headers\":{},\"userData\":{\"label\":\"match\"}}",
	"method": "GET",
	"orderNo": 1671053211954,
	"retryCount": 0,
	"uniqueKey": "https://www.livesport.com/en/match/EPqGnLRn",
	"url": "https://www.livesport.com/en/match/EPqGnLRn/#/match-summary/match-summary"
}