{
	"id": "XMWbvXYNKg392E8",
	"json": "{\"id\":\"XMWbvXYNKg392E8\",\"url\":\"https://www.livesport.com/en/match/K8w9bRQ7/#/match-summary/match-summary\",\"uniqueKey\":\"https://www.livesport.com/en/match/K8w9bRQ7\",\"method\":\"GET\",\"noRetry\":false,\"retryCount\":0,\"errorMessages\":[],\"headers\":{},\"userData\":{\"label\":\"match\"}}",
	"method": "GET",
	"orderNo": 1671053211960,
	"retryCount": 0,
	"uniqueKey": "https://www.livesport.com/en/match/K8w9bRQ7",
	"url": "https://www.livesport.com/en/match/K8w9bRQ7/#/match-summary/match-summary"
}