{
	"id": "zBhZmuRPjp2rvBB",
	"json": "{\"id\":\"zBhZmuRPjp2rvBB\",\"url\":\"https://www.livesport.com/en/match/691C23Km/#/match-summary/match-statistics/0\",\"loadedUrl\":\"https://www.livesport.com/en/match/691C23Km/#/match-summary/match-statistics/0\",\"uniqueKey\":\"https://www.livesport.com/en/match/691C23Km\",\"method\":\"GET\",\"noRetry\":false,\"retryCount\":0,\"errorMessages\":[],\"headers\":{},\"userData\":{\"label\":\"match\",\"__crawlee\":{\"state\":4}},\"handledAt\":\"2022-12-12T19:20:22.331Z\"}",
	"method": "GET",
	"orderNo": null,
	"retryCount": 0,
	"uniqueKey": "https://www.livesport.com/en/match/691C23Km",
	"url": "https://www.livesport.com/en/match/691C23Km/#/match-summary/match-statistics/0"
}